bingus/__init__.py
bingus/environ/__init__.py
bingus/environ/environ.py
bingus/environ/exceptions.py
bingus/file/__init__.py
bingus/file/file.py
bingus/logging/__init__.py
bingus/logging/logging.py
bingus-0.3.0.dist-info/WHEEL
bingus-0.3.0.dist-info/METADATA
bingus-0.3.0.dist-info/RECORD
